word_alignment_visualization/__init__.py
word_alignment_visualization/show_alignment.py
word_alignment_visualization/static/word_alignment_viz.css
word_alignment_visualization/static/word_alignment_viz.js
word_alignment_visualization-0.1.3.dist-info/LICENSE
word_alignment_visualization-0.1.3.dist-info/METADATA
word_alignment_visualization-0.1.3.dist-info/WHEEL
word_alignment_visualization-0.1.3.dist-info/top_level.txt
word_alignment_visualization-0.1.3.dist-info/RECORD
