Metadata-Version: 2.1
Name: word-alignment-visualization
Version: 0.1.3
License-File: LICENSE
Requires-Dist: ipython
